README.md
setup.py
mark_search/__init__.py
mark_search/analyzers.py
mark_search/index.py
mark_search/postings_prefetch.py
mark_search/query_components.py
mark_search/query_context.py
mark_search/query_executor.py
mark_search/query_result.py
mark_search/query_validator.py
mark_search/row_parsers.py
mark_search.egg-info/PKG-INFO
mark_search.egg-info/SOURCES.txt
mark_search.egg-info/dependency_links.txt
mark_search.egg-info/not-zip-safe
mark_search.egg-info/requires.txt
mark_search.egg-info/top_level.txt
mark_search/combine_scores/__init__.py
mark_search/combine_scores/wrapped.pyx