Metadata-Version: 1.0
Name: mark-search
Version: 0.2.4
Summary: !
Home-page: UNKNOWN
Author: Mark Hudson
Author-email: mark.cd.hudson@gmail.com
License: Apache 2.0
Platform: UNKNOWN
